MANIFEST.in
setup.py
src/ldapgroups/README.txt
src/ldapgroups/__init__.py
src/ldapgroups/configure.zcml
src/ldapgroups/groupfolder.py
src/ldapgroups/i18n.py
src/ldapgroups/interfaces.py
src/ldapgroups.egg-info/PKG-INFO
src/ldapgroups.egg-info/SOURCES.txt
src/ldapgroups.egg-info/dependency_links.txt
src/ldapgroups.egg-info/not-zip-safe
src/ldapgroups.egg-info/requires.txt
src/ldapgroups.egg-info/top_level.txt
src/ldapgroups/browser/__init__.py
src/ldapgroups/browser/configure.zcml
src/ldapgroups/browser/contents.pt
src/ldapgroups/browser/contents.py
src/ldapgroups/tests/__init__.py
src/ldapgroups/tests/fakeadapter.py
src/ldapgroups/tests/test_readme.py