Metadata-Version: 1.0
Name: ldapgroups
Version: 0.2
Summary: A read-only Zope3 GroupFolder implementation that reflects groups on an LDAP server.
